{
  "UniFiSwitch": {
    "US-6XG-150": {
      "INDEX": 0,
      "NAME": "US-6XG-150",
      "BOARDID": "eb23",
      "BOMREV": "113-02604",
      "DESC": "UBNT UniFiSwitch 6XG",
      "FILE": "us_bcm5616_factory.py",
      "T1FILE": "us_bcm5616_mfg.py",
      "QRCHECK": "True",
      "SW_ID": "0201",
      "DOWNLOAD_FILE": [
        {
          "SRC_PATH": "images/fcd-image/usw-fw",
          "DST_PATH": "usw-fw",
          "FILES": [
            "unifiswitch-6xg150-fw.bin",
            "unifiswitch-6xg150-mfg.bin"
          ]
        },
        {
          "SRC_PATH": "images/tools/",
          "DST_PATH": "tools/",
          "FILES": []
        },
        {
          "SRC_PATH": "images/tools/common",
          "DST_PATH": "tools/common",
          "FILES": [
            "sshd_config",
            "tmux.conf",
            "x86-64k-ee",
            "aarch64-rpi4-64k-ee"
          ]
        }
      ],
      "CREATE_LINK": [
        [
          "tftp/images/eb23.bin",
          "../usw-fw/unifiswitch-6xg150-fw.bin"
        ],
        [
          "tftp/images/eb23-mfg.bin",
          "../usw-fw/unifiswitch-6xg150-mfg.bin"
        ]
      ]
    }
  }
}