{
  "UniFiAccess": {
    "UA-HUB": {
      "INDEX": 2,
      "NAME": "UA-HUB",
      "BOARDID": "ec36",
      "BOMREV": "113-02964",
      "DESC": "UniFi Access Hub",
      "FILE": "ua_mt7621_factory3.py",
      "T1FILE": "",
      "QRCHECK": "True",
      "FCD_ID": "0012",
      "SW_ID": "1d01",
      "DOWNLOAD_FILE": [
        {
          "SRC_PATH": "images/fcd-image/ua-fw",
          "DST_PATH": "ua-fw",
          "FILES": [
            "DA.mt7621.v4.0.11.338.g08509fe.201103.1305.bin",
            "ua-gate-nor-v2.bin"
          ]
        },
        {
          "SRC_PATH": "images/tools/common",
          "DST_PATH": "tools/common",
          "FILES": [
            "sshd_config",
            "tmux.conf",
            "x86-64k-ee",
            "aarch64-rpi4-64k-ee"
          ]
        }
      ],
      "CREATE_LINK": [
        [
          "tftp/images/ec36-t1.bin",
          "../ua-fw/ua-hub-t1.bin"
        ],
        [
          "tftp/ua-fw/ua-hub-t1.bin",
          "../ua-fw/ua-gate-nor-v2.bin"
        ],
        [
          "tftp/images/ec36-fw.bin",
          "../ua-fw/ua-hub-fw.bin"
        ],
        [
          "tftp/ua-fw/ua-hub-fw.bin",
          "../ua-fw/DA.mt7621.v4.0.11.338.g08509fe.201103.1305.bin"
        ]
      ]
    }
  }
}