{
  "UniFiAP6": {
    "UEX-M": {
      "INDEX": 0,
      "NAME": "UEX-M",
      "BOARDID": "a674",
      "BOMREV": "113-01184",
      "DESC": "UniFi6 Express Mesh",
      "FILE": "u6_ipq5018_bspfactory.py",
      "T1FILE": "u6_ipq5018_mfg.py",
      "QRCHECK": "True",
      "SW_ID": "0601",
      "DOWNLOAD_FILE": [
        {
          "SRC_PATH": "images/tools/common",
          "DST_PATH": "tools/common",
          "FILES": [
            "sshd_config",
            "tmux.conf",
            "x86-64k-ee",
            "aarch64-rpi4-4k-ee",
            "aarch64-rpi4-64k-ee"
          ]
        },
        {
          "SRC_PATH": "images/fcd-image/a667",
          "DST_PATH": "a674",
          "FILES": [
            "UEX.ipq5018.v1.0.0.277609a.221115.1047.bin",
            "uImage-v1.0.0",
            "unifi-uex-0.0.3.135-g4086284b_ipq5018_uex_u-boot.mbn",
            "u6-express-v2.img",
            "u6-express-v2_nor.bin"
          ]
        }
      ],
      "CREATE_LINK": [
        [
          "tftp/images/a674-nor.bin",
          "../a674/u6-express-v2_nor.bin"
        ],
        [
          "tftp/images/a674-emmc.img",
          "../a674/u6-express-v2.img"
        ],
        [
          "tftp/images/a674-fw.bin",
          "../a674/UEX.ipq5018.v1.0.0.277609a.221115.1047.bin"
        ],
        [
          "tftp/images/a674-uboot.mbn",
          "../a674/unifi-uex-0.0.1.129-gc746286d_ipq5018_uex_u-boot.mbn"
        ],
        [
          "tftp/images/a674-loader.img",
          "../a674/uImage-v1.0.0"
        ]
      ]
    }
  }
}
