{
  "UniFiDream":
  {
    "UDM":{
      "INDEX"       : 0,
      "NAME"        : "UDM",
      "BOARDID"     : "ea11",
      "BOMREV"      : "113-00623",
      "DESC"        : "UniFi Dream Machine",
      "FILE"        : "udm_alpine_factory.py",
      "T1FILE"      : "",
      "QRCHECK"     : "True"
    },

    "UDM-SE":{
      "INDEX"       : 1,
      "NAME"        : "UDM-SE",
      "BOARDID"     : "ea13",
      "BOMREV"      : "113-00618",
      "DESC"        : "UniFi Dream Machine Special",
      "FILE"        : "udm_alpine_factory.py",
      "T1FILE"      : "",
      "QRCHECK"     : "True"
    },

    "UDM-PRO":{
      "INDEX"       : 2,
      "NAME"        : "UDM-PRO",
      "BOARDID"     : "ea15",
      "BOMREV"      : "113-00723",
      "DESC"        : "UniFi Dream Machine Pro",
      "FILE"        : "udm_alpine_factory.py",
      "T1FILE"      : "",
      "QRCHECK"     : "True"
    },

    "UDM-B":{
      "INDEX"       : 3,
      "NAME"        : "UDM-B",
      "BOARDID"     : "ec25",
      "BOMREV"      : "113-00622",
      "DESC"        : "UniFi One Dream Machine Beacon",
      "FILE"        : "us_mt7621_factory.py",
      "T1FILE"      : "unifi_mt7621_mfg.py",
      "QRCHECK"     : "True",
      "FCD_ID"      : "0005",
      "SW_ID"       : "0701"
    },

    "UDM-XG":{
      "INDEX"       : 4,
      "NAME"        : "UDM-XG",
      "BOARDID"     : "ea17",
      "BOMREV"      : "113-02719",
      "DESC"        : "UniFi One Dream Machine XG",
      "FILE"        : "udm_xeon1521_factory.py",
      "T1FILE"      : "",
      "QRCHECK"     : "True"
    },

    "UDM-LOCO":{
      "INDEX"       : 5,
      "NAME"        : "UDM-LOCO",
      "BOARDID"     : "ec28",
      "BOMREV"      : "113-00633",
      "DESC"        : "UniFi One Dream Machine LOCO",
      "FILE"        : "udm_mt7622_factory.py",
      "T1FILE"      : "",
      "QRCHECK"     : "True",
      "FCD_ID"      : "0005",
      "SW_ID"       : "0701"
    }
  },

  "UniFiSwitch":
  {
    "US-FLEX":{
      "INDEX"       : 0,
      "NAME"        : "US-FLEX",
      "BOARDID"     : "ed10",
      "BOMREV"      : "113-02767",
      "DESC"        : "UniFi Switch Flex",
      "FILE"        : "us_mt7621_factory.py",
      "T1FILE"      : "unifi_mt7621_mfg.py",
      "QRCHECK"     : "True",
      "FCD_ID"      : "0002",
      "SW_ID"       : "0201"
    },

    "USW-24-PRO-POE":{
      "INDEX"       : 1,
      "NAME"        : "USW-24-PRO-POE",
      "BOARDID"     : "eb36",
      "BOMREV"      : "113-02779",
      "DESC"        : "UBNT UniFiSwitch 24-Port Pro PoE",
      "FILE"        : "us_bcm5616_factory.py",
      "T1FILE"      : "us_mfg.py",
      "QRCHECK"     : "True",
      "FCD_ID"      : "0002",
      "SW_ID"       : "0201"
    },

    "USW-48-PRO-POE":{
      "INDEX"       : 2,
      "NAME"        : "USW-48-PRO-POE",
      "BOARDID"     : "eb67",
      "BOMREV"      : "113-02757",
      "DESC"        : "UBNT UniFiSwitch 48-Port Pro PoE",
      "FILE"        : "us_bcm5616_factory.py",
      "T1FILE"      : "us_mfg.py",
      "QRCHECK"     : "True",
      "FCD_ID"      : "0002",
      "SW_ID"       : "0201"
    },

    "US-6XG-150":{
      "INDEX"       : 3,
      "NAME"        : "US-6XG-150",
      "BOARDID"     : "eb23",
      "BOMREV"      : "113-02604",
      "DESC"        : "UBNT UniFiSwitch 6XG",
      "FILE"        : "us_factory.py",
      "T1FILE"      : "us_mfg.py",
      "QRCHECK"     : "True",
      "FCD_ID"      : "0002",
      "SW_ID"       : "0201"
    },

    "ULS-RPS":{
      "INDEX"       : 4,
      "NAME"        : "ULS-RPS",
      "BOARDID"     : "ed11",
      "BOMREV"      : "113-02781",
      "DESC"        : "UniFi Life Saver RPS",
      "FILE"        : "us_mt7621_factory.py",
      "T1FILE"      : "unifi_mt7621_mfg.py",
      "QRCHECK"     : "True",
      "FCD_ID"      : "0002",
      "SW_ID"       : "0201"
    },

    "USW-16-POE":{
      "INDEX"       : 5,
      "NAME"        : "USW-16-POE",
      "BOARDID"     : "ed20",
      "BOMREV"      : "113-02848",
      "DESC"        : "UBNT UniFiSwitch 16 POE",
      "FILE"        : "us_rtl838x_factory.py",
      "T1FILE"      : "us_rtl838x_mfg.py",
      "QRCHECK"     : "True",
      "FCD_ID"      : "0002",
      "SW_ID"       : "0201"
    },

    "USW-24-POE":{
      "INDEX"       : 6,
      "NAME"        : "USW-24-POE",
      "BOARDID"     : "ed21",
      "BOMREV"      : "113-02831",
      "DESC"        : "UBNT UniFiSwitch 24 POE",
      "FILE"        : "us_rtl838x_factory.py",
      "T1FILE"      : "us_rtl838x_mfg.py",
      "QRCHECK"     : "True",
      "FCD_ID"      : "0002",
      "SW_ID"       : "0201"
    },

    "USW-48-POE":{
      "INDEX"       : 7,
      "NAME"        : "USW-48-POE",
      "BOARDID"     : "ed22",
      "BOMREV"      : "113-02865",
      "DESC"        : "UBNT UniFiSwitch 48 POE",
      "FILE"        : "us_rtl838x_factory.py",
      "T1FILE"      : "us_rtl838x_mfg.py",
      "QRCHECK"     : "True",
      "FCD_ID"      : "0002",
      "SW_ID"       : "0201"
    },

    "USW-16":{
      "INDEX"       : 8,
      "NAME"        : "USW-16",
      "BOARDID"     : "ed23",
      "BOMREV"      : "113-02943",
      "DESC"        : "UBNT UniFiSwitch 16",
      "FILE"        : "us_rtl838x_factory.py",
      "T1FILE"      : "us_rtl838x_mfg.py",
      "QRCHECK"     : "True",
      "FCD_ID"      : "0002",
      "SW_ID"       : "0201"
    },

    "USW-24":{
      "INDEX"       : 9,
      "NAME"        : "USW-24",
      "BOARDID"     : "ed24",
      "BOMREV"      : "113-02944",
      "DESC"        : "UBNT UniFiSwitch 24",
      "FILE"        : "us_rtl838x_factory.py",
      "T1FILE"      : "us_rtl838x_mfg.py",
      "QRCHECK"     : "True",
      "FCD_ID"      : "0002",
      "SW_ID"       : "0201"
    },

    "USW-LITE-16-POE":{
      "INDEX"       : 10,
      "NAME"        : "USW-LITE-16-POE",
      "BOARDID"     : "ed26",
      "BOMREV"      : "113-02945",
      "DESC"        : "UBNT UniFiSwitch Lite 16 POE",
      "FILE"        : "us_rtl838x_factory.py",
      "T1FILE"      : "us_rtl838x_mfg.py",
      "QRCHECK"     : "True",
      "FCD_ID"      : "0002",
      "SW_ID"       : "0201"
    },

    "USW-LEAF":{
      "INDEX"       : 11,
      "NAME"        : "USW-LEAF",
      "BOARDID"     : "f060",
      "BOMREV"      : "113-02997",
      "DESC"        : "UniFi Super Switch 48-port",
      "FILE"        : "us_udc-alpine_factory.py",
      "T1FILE"      : "us_udc-alpine_mfg.py",
      "QRCHECK"     : "True",
      "FCD_ID"      : "0002",
      "SW_ID"       : "0201"
    },

    "USW-MINI":{
      "INDEX"       : 12,
      "NAME"        : "USW-FLEX-MINI",
      "BOARDID"     : "ed30",
      "BOMREV"      : "113-02851",
      "DESC"        : "UniFi Switch Flex Mini",
      "FILE"        : "us_m487_factory.py",
      "T1FILE"      : "",
      "QRCHECK"     : "True",
      "FCD_ID"      : "0002",
      "SW_ID"       : "0201"
    },

    "USW-LITE-8-POE":{
      "INDEX"       : 13,
      "NAME"        : "USW-LITE-8-POE",
      "BOARDID"     : "ed2a",
      "BOMREV"      : "113-02992",
      "DESC"        : "UBNT UniFiSwitch Lite 8 POE",
      "FILE"        : "us_rtl838x_factory.py",
      "T1FILE"      : "us_rtl838x_mfg.py",
      "QRCHECK"     : "True",
      "FCD_ID"      : "0002",
      "SW_ID"       : "0201"
    }
  },

  "UniFiAP":
  {
    "UAP-FLEX-HD":{
      "INDEX"       : 0,
      "NAME"        : "UAP-FLEXHD",
      "BOARDID"     : "ec26",
      "BOMREV"      : "113-00641",
      "DESC"        : "UniFi AP Flex HD",
      "FILE"        : "us_mt7621_factory.py",
      "T1FILE"      : "unifi_mt7621_mfg.py",
      "QRCHECK"     : "True",
      "FCD_ID"      : "0004",
      "SW_ID"       : "0601"
    },

    "UAP-Building-Bridge":{
      "INDEX"       : 1,
      "NAME"        : "UAP-UBB",
      "BOARDID"     : "dc98",
      "BOMREV"      : "113-00694",
      "DESC"        : "UniFi AP Building Bridge",
      "FILE"        : "uap_ipq40xx_factory.py",
      "T1FILE"      : "uap_ipq40xx_mfg.py",
      "QRCHECK"     : "True",
      "FCD_ID"      : "0004",
      "SW_ID"       : "0601"
    },

    "UAP-Industrial":{
      "INDEX"       : 2,
      "NAME"        : "UAP-Industrial",
      "BOARDID"     : "ec2a",
      "BOMREV"      : "113-00710",
      "DESC"        : "UniFi AP nanoHD industrial",
      "FILE"        : "us_mt7621_factory.py",
      "T1FILE"      : "",
      "QRCHECK"     : "True",
      "FCD_ID"      : "0004",
      "SW_ID"       : "0601"
    },

    "UAP-IW-HD":{
      "INDEX"       : 0,
      "NAME"        : "UAP-IWHD",
      "BOARDID"     : "ec22",
      "BOMREV"      : "113-00600",
      "DESC"        : "UniFi AP IW HD",
      "FILE"        : "us_mt7621_factory.py",
      "T1FILE"      : "unifi_mt7621_mfg.py",
      "QRCHECK"     : "True",
      "FCD_ID"      : "0004",
      "SW_ID"       : "0601"
    }
  },

  "UniFiSG":
  {
  },

  "Amplifi":
  {
    "AFi-AX-R":{
      "INDEX"       : 0,
      "NAME"        : "AFi-AX-R",
      "BOARDID"     : "da11",
      "BOMREV"      : "113-00605",
      "DESC"        : "Amplifi AX Router",
      "FILE"        : "afi_ipq807x_factory.py",
      "T1FILE"      : "",
      "QRCHECK"     : "False"
    },

    "AFi-AX-P":{
      "INDEX"       : 1,
      "NAME"        : "AFi-AX-P",
      "BOARDID"     : "da12",
      "BOMREV"      : "113-00657",
      "DESC"        : "Amplifi AX Mesh Point",
      "FILE"        : "afi_ipq807x_factory.py",
      "T1FILE"      : "",
      "QRCHECK"     : "False"
    }
  },

  "AirFiber":
  {
    "LTU-Pro":{
      "INDEX"       : 0,
      "NAME"        : "LTU-Pro",
      "BOARDID"     : "ae06",
      "BOMREV"      : "113-00680",
      "DESC"        : "AirFiber LTU-LR",
      "FILE"        : "af_factory.py",
      "T1FILE"      : "",
      "QRCHECK"     : "False",
      "FCD_ID"      : "000a",
      "SW_ID"       : "1001"
    },

    "LTU-Lite":{
      "INDEX"       : 1,
      "NAME"        : "LTU-Lite",
      "BOARDID"     : "ae08",
      "BOMREV"      : "113-00708",
      "DESC"        : "AirFiber LTU-Lite",
      "FILE"        : "af_factory.py",
      "T1FILE"      : "",
      "QRCHECK"     : "False",
      "FCD_ID"      : "000a",
      "SW_ID"       : "1001"
    },

    "AF60":{
      "INDEX"       : 2,
      "NAME"        : "AF60",
      "BOARDID"     : "dc9b",
      "BOMREV"      : "113-00720",
      "DESC"        : "AirFiber 60",
      "FILE"        : "af_ipq40xx_factory.py",
      "T1FILE"      : "af_ipq40xx_mfg.py",
      "QRCHECK"     : "False",
      "FCD_ID"      : "000a",
      "SW_ID"       : "1001"
    },

    "LTU-LR":{
      "INDEX"       : 3,
      "NAME"        : "LTU-LR",
      "BOARDID"     : "ae0b",
      "BOMREV"      : "113-00727",
      "DESC"        : "AirFiber LTU-LR",
      "FILE"        : "af_factory.py",
      "T1FILE"      : "",
      "QRCHECK"     : "False",
      "FCD_ID"      : "000a",
      "SW_ID"       : "1001"
    }
  },

  "UniFiNVR":
  {
    "UNVR-4":{
      "INDEX"       : 0,
      "NAME"        : "UNVR-4",
      "BOARDID"     : "ea16",
      "BOMREV"      : "113-02832",
      "DESC"        : "UniFi NVR 4-Bay",
      "FILE"        : "unas_alpine_factory.py",
      "T1FILE"      : "",
      "QRCHECK"     : "True",
      "FCD_ID"      : "0006",
      "SW_ID"       : "0801"
    },

    "UNVR-8":{
      "INDEX"       : 1,
      "NAME"        : "UNVR-8",
      "BOARDID"     : "ea18",
      "BOMREV"      : "113-02904",
      "DESC"        : "UniFi NVR 8-Bay",
      "FILE"        : "unas_alpine_factory.py",
      "T1FILE"      : "",
      "QRCHECK"     : "True",
      "FCD_ID"      : "0006",
      "SW_ID"       : "0801"
    }
  },

  "UniFiVOIP":
  {
    "UVP-FLEX":{
      "INDEX"       : 0,
      "NAME"        : "UVP-FLEX",
      "BOARDID"     : "ef0d",
      "BOMREV"      : "113-02808",
      "DESC"        : "UniFi VOIP FLEX",
      "FILE"        : "uvp_dvf9918_factory.py",
      "T1FILE"      : "",
      "QRCHECK"     : "True",
      "FCD_ID"      : "0007",
      "SW_ID"       : "0a01"
    }
  },

  "airMAX":
  {
    "GBE":{
      "INDEX"       : 0,
      "NAME"        : "GBE",
      "BOARDID"     : "dc9a",
      "BOMREV"      : "113-00714",
      "DESC"        : "GBE",
      "FILE"        : "am_ipq40xx_factory.py",
      "T1FILE"      : "am_ipq40xx_mfg.py",
      "QRCHECK"     : "False",
      "FCD_ID"      : "000b",
      "SW_ID"       : "1201"
    },

    "GBE-LR":{
      "INDEX"       : 1,
      "NAME"        : "GBE-LR",
      "BOARDID"     : "dc99",
      "BOMREV"      : "113-00709",
      "DESC"        : "GBE",
      "FILE"        : "am_ipq40xx_factory.py",
      "T1FILE"      : "am_ipq40xx_mfg.py",
      "QRCHECK"     : "False",
      "FCD_ID"      : "000b",
      "SW_ID"       : "1201"
    },

    "PrismAP":{
      "INDEX"       : 2,
      "NAME"        : "PrismAP",
      "BOARDID"     : "dc97",
      "BOMREV"      : "113-00697",
      "DESC"        : "PrismStation AP",
      "FILE"        : "am_qca955x_factory.py",
      "T1FILE"      : "",
      "QRCHECK"     : "False",
      "FCD_ID"      : "000b",
      "SW_ID"       : "1201"
    }
  },

  "UniFiProtect":
  {
    "UFP-SENSE":{
      "INDEX"       : 0,
      "NAME"        : "UFP-SENSE",
      "BOARDID"     : "a912",
      "BOMREV"      : "113-02823",
      "DESC"        : "UniFi Protect Sensor",
      "FILE"        : "ufp_efr32_factory.py",
      "T1FILE"      : "",
      "QRCHECK"     : "False",
      "FCD_ID"      : "000d",
      "SW_ID"       : "1601"
    },
    "UFP-LOCK-R":{
      "INDEX"       : 1,
      "NAME"        : "UFP-LOCK-R",
      "BOARDID"     : "a911",
      "BOMREV"      : "113-02765",
      "DESC"        : "UniFi Protect Doorlock",
      "FILE"        : "ufp_efr32_factory.py",
      "T1FILE"      : "",
      "QRCHECK"     : "False",
      "FCD_ID"      : "000d",
      "SW_ID"       : "1602"
    }
  },

  "USP":
  {
    "USP-Plug":{
      "INDEX"       : 0,
      "NAME"        : "USP-Plug",
      "BOARDID"     : "ee73",
      "BOMREV"      : "113-00731",
      "DESC"        : "UniFi smart plug",
      "FILE"        : "usp_esp8266_factory.py",
      "T1FILE"      : "",
      "QRCHECK"     : "True",
      "FCD_ID"      : "000e",
      "SW_ID"       : "1801"
    },
    "USP3":{
      "INDEX"       : 1,
      "NAME"        : "USP3",
      "BOARDID"     : "e643",
      "BOMREV"      : "113-00364",
      "DESC"        : "Unifi Smart Plug 3",
      "FILE"        : "unifi_ar9331_factory.py",
      "T1FILE"      : "",
      "QRCHECK"     : "True",
      "FCD_ID"      : "000e",
      "SW_ID"       : "1801"
    },
    "USP8":{
      "INDEX"       : 1,
      "NAME"        : "USP8",
      "BOARDID"     : "e648",
      "BOMREV"      : "113-00365",
      "DESC"        : "Unifi Smart Plug 8",
      "FILE"        : "unifi_ar9331_factory.py",
      "T1FILE"      : "",
      "QRCHECK"     : "True",
      "FCD_ID"      : "000e",
      "SW_ID"       : "1801"
    }
  },

  "UniFiVideo":
  {
    "UVC-G4PRO":{
      "INDEX"       : 0,
      "NAME"        : "UVC-G4",
      "BOARDID"     : "a563",
      "BOMREV"      : "113-02574",
      "DESC"        : "GBE",
      "FILE"        : "uvc_factory.py",
      "T1FILE"      : "",
      "QRCHECK"     : "False",
      "FCD_ID"      : "0009",
      "SW_ID"       : "0e04"
     },
     "UVC-G3BATTERY":{
      "INDEX"       : 1,
      "NAME"        : "UVC-G3",
      "BOARDID"     : "a580",
      "BOMREV"      : "113-02692",
      "DESC"        : "GBE",
      "FILE"        : "uvc_factory.py",
      "T1FILE"      : "",
      "QRCHECK"     : "False",
      "FCD_ID"      : "0009",
      "SW_ID"       : "0e03"
     }
  }
}
